<annotation>
    <folder>panos</folder>
    <filename>pano_012215.png</filename>
    <size>
        <width>3840</width>
        <height>1920</height>
        <depth>3</depth>
    </size>
    <segmented>0</segmented>
    <object>
        <name>door-6600-clark</name>
        <pose>Unspecified</pose>
        <truncated>0</truncated>
        <occluded>0</occluded>
        <difficult>0</difficult>
        <polygon>
            <x1>3211</x1>
            <y1>1167</y1>
            <x2>3068</x2>
            <y2>1175</y2>
            <x3>3088</x3>
            <y3>784</y3>
            <x4>3226</x4>
            <y4>807</y4>
        </polygon>
        <bndbox>
            <xmin>3068</xmin>
            <ymin>784</ymin>
            <xmax>3226</xmax>
            <ymax>1175</ymax>
        </bndbox>
    </object>
    <object>
        <name>house_number-6600-clark</name>
        <pose>Unspecified</pose>
        <truncated>0</truncated>
        <occluded>0</occluded>
        <difficult>0</difficult>
        <bndbox>
            <xmin>2957</xmin>
            <ymin>892</ymin>
            <xmax>3039</xmax>
            <ymax>926</ymax>
        </bndbox>
    </object>
</annotation>