<annotation>
    <folder>panos</folder>
    <filename>pano_118989.png</filename>
    <size>
        <width>3840</width>
        <height>1920</height>
        <depth>3</depth>
    </size>
    <segmented>0</segmented>
    <object>
        <name>door-6631-saint_laurent</name>
        <pose>Unspecified</pose>
        <truncated>0</truncated>
        <occluded>0</occluded>
        <difficult>0</difficult>
        <polygon>
            <x1>3004</x1>
            <y1>711</y1>
            <x2>3251</x2>
            <y2>756</y2>
            <x3>3241</x3>
            <y3>1334</y3>
            <x4>2979</x4>
            <y4>1376</y4>
        </polygon>
        <bndbox>
            <xmin>2979</xmin>
            <ymin>711</ymin>
            <xmax>3251</xmax>
            <ymax>1376</ymax>
        </bndbox>
    </object>
    <object>
        <name>door-6633-saint_laurent</name>
        <pose>Unspecified</pose>
        <truncated>0</truncated>
        <occluded>0</occluded>
        <difficult>0</difficult>
        <polygon>
            <x1>3004</x1>
            <y1>711</y1>
            <x2>3251</x2>
            <y2>756</y2>
            <x3>3241</x3>
            <y3>1334</y3>
            <x4>2979</x4>
            <y4>1376</y4>
        </polygon>
        <bndbox>
            <xmin>2979</xmin>
            <ymin>711</ymin>
            <xmax>3251</xmax>
            <ymax>1376</ymax>
        </bndbox>
    </object>
    <object>
        <name>door-6635-saint_laurent</name>
        <pose>Unspecified</pose>
        <truncated>0</truncated>
        <occluded>0</occluded>
        <difficult>0</difficult>
        <polygon>
            <x1>3004</x1>
            <y1>711</y1>
            <x2>3251</x2>
            <y2>756</y2>
            <x3>3241</x3>
            <y3>1334</y3>
            <x4>2979</x4>
            <y4>1376</y4>
        </polygon>
        <bndbox>
            <xmin>2979</xmin>
            <ymin>711</ymin>
            <xmax>3251</xmax>
            <ymax>1376</ymax>
        </bndbox>
    </object>
    <object>
        <name>house_number-6631-saint_laurent</name>
        <pose>Unspecified</pose>
        <truncated>0</truncated>
        <occluded>0</occluded>
        <difficult>0</difficult>
        <bndbox>
            <xmin>2845</xmin>
            <ymin>1296</ymin>
            <xmax>2936</xmax>
            <ymax>1324</ymax>
        </bndbox>
    </object>
    <object>
        <name>house_number-6633-saint_laurent</name>
        <pose>Unspecified</pose>
        <truncated>0</truncated>
        <occluded>0</occluded>
        <difficult>0</difficult>
        <bndbox>
            <xmin>2854</xmin>
            <ymin>1181</ymin>
            <xmax>2937</xmax>
            <ymax>1224</ymax>
        </bndbox>
    </object>
    <object>
        <name>house_number-6633-saint_laurent</name>
        <pose>Unspecified</pose>
        <truncated>0</truncated>
        <occluded>0</occluded>
        <difficult>0</difficult>
        <bndbox>
            <xmin>2998</xmin>
            <ymin>835</ymin>
            <xmax>3135</xmax>
            <ymax>883</ymax>
        </bndbox>
    </object>
    <object>
        <name>house_number-6635-saint_laurent</name>
        <pose>Unspecified</pose>
        <truncated>0</truncated>
        <occluded>0</occluded>
        <difficult>0</difficult>
        <bndbox>
            <xmin>2852</xmin>
            <ymin>1045</ymin>
            <xmax>2945</xmax>
            <ymax>1089</ymax>
        </bndbox>
    </object>
    <object>
        <name>house_number-6635-saint_laurent</name>
        <pose>Unspecified</pose>
        <truncated>0</truncated>
        <occluded>0</occluded>
        <difficult>0</difficult>
        <bndbox>
            <xmin>3005</xmin>
            <ymin>798</ymin>
            <xmax>3138</xmax>
            <ymax>848</ymax>
        </bndbox>
    </object>
</annotation>