<annotation>
    <folder>panos</folder>
    <filename>pano_257253.png</filename>
    <size>
        <width>3840</width>
        <height>1920</height>
        <depth>3</depth>
    </size>
    <segmented>0</segmented>
    <object>
        <name>door-7070-saint_urbain</name>
        <pose>Unspecified</pose>
        <truncated>0</truncated>
        <occluded>0</occluded>
        <difficult>0</difficult>
        <polygon>
            <x1>3141</x1>
            <y1>907</y1>
            <x2>3327</x2>
            <y2>928</y2>
            <x3>3320</x3>
            <y3>1161</y3>
            <x4>3124</x4>
            <y4>1185</y4>
        </polygon>
        <bndbox>
            <xmin>3124</xmin>
            <ymin>907</ymin>
            <xmax>3327</xmax>
            <ymax>1185</ymax>
        </bndbox>
    </object>
    <object>
        <name>house_number-7070-saint_urbain</name>
        <pose>Unspecified</pose>
        <truncated>0</truncated>
        <occluded>0</occluded>
        <difficult>0</difficult>
        <bndbox>
            <xmin>3194</xmin>
            <ymin>812</ymin>
            <xmax>3295</xmax>
            <ymax>866</ymax>
        </bndbox>
    </object>
</annotation>