<annotation>
    <folder>panos</folder>
    <filename>pano_038763.png</filename>
    <size>
        <width>3840</width>
        <height>1920</height>
        <depth>3</depth>
    </size>
    <segmented>0</segmented>
    <object>
        <name>door-6546-clark</name>
        <pose>Unspecified</pose>
        <truncated>0</truncated>
        <occluded>0</occluded>
        <difficult>0</difficult>
        <polygon>
            <x1>2656</x1>
            <y1>841</y1>
            <x2>2805</x2>
            <y2>842</y2>
            <x3>2784</x3>
            <y3>1208</y3>
            <x4>2641</x4>
            <y4>1193</y4>
        </polygon>
        <bndbox>
            <xmin>2641</xmin>
            <ymin>841</ymin>
            <xmax>2805</xmax>
            <ymax>1208</ymax>
        </bndbox>
    </object>
    <object>
        <name>house_number-6546-clark</name>
        <pose>Unspecified</pose>
        <truncated>0</truncated>
        <occluded>0</occluded>
        <difficult>0</difficult>
        <bndbox>
            <xmin>2701</xmin>
            <ymin>800</ymin>
            <xmax>2761</xmax>
            <ymax>856</ymax>
        </bndbox>
    </object>
</annotation>