<annotation>
    <folder>panos</folder>
    <filename>pano_276255.png</filename>
    <size>
        <width>3840</width>
        <height>1920</height>
        <depth>3</depth>
    </size>
    <segmented>0</segmented>
    <object>
        <name>door-7160-saint_laurent</name>
        <pose>Unspecified</pose>
        <truncated>0</truncated>
        <occluded>0</occluded>
        <difficult>0</difficult>
        <polygon>
            <x1>2780</x1>
            <y1>795</y1>
            <x2>2768</x2>
            <y2>1200</y2>
            <x3>2899</x3>
            <y3>1161</y3>
            <x4>2909</x4>
            <y4>816</y4>
        </polygon>
        <bndbox>
            <xmin>2768</xmin>
            <ymin>795</ymin>
            <xmax>2909</xmax>
            <ymax>1200</ymax>
        </bndbox>
    </object>
    <object>
        <name>house_number-7160-saint_laurent</name>
        <pose>Unspecified</pose>
        <truncated>0</truncated>
        <occluded>0</occluded>
        <difficult>0</difficult>
        <bndbox>
            <xmin>2805</xmin>
            <ymin>737</ymin>
            <xmax>2866</xmax>
            <ymax>783</ymax>
        </bndbox>
    </object>
</annotation>