<annotation>
    <folder>panos</folder>
    <filename>pano_125790.png</filename>
    <size>
        <width>3840</width>
        <height>1920</height>
        <depth>3</depth>
    </size>
    <segmented>0</segmented>
    <object>
        <name>door-6548-saint_laurent</name>
        <pose>Unspecified</pose>
        <truncated>0</truncated>
        <occluded>0</occluded>
        <difficult>0</difficult>
        <polygon>
            <x1>2778</x1>
            <y1>822</y1>
            <x2>2759</x2>
            <y2>1306</y2>
            <x3>3017</x3>
            <y3>1304</y3>
            <x4>3030</x4>
            <y4>829</y4>
        </polygon>
        <bndbox>
            <xmin>2759</xmin>
            <ymin>822</ymin>
            <xmax>3030</xmax>
            <ymax>1306</ymax>
        </bndbox>
    </object>
    <object>
        <name>door-6546-saint_laurent</name>
        <pose>Unspecified</pose>
        <truncated>0</truncated>
        <occluded>0</occluded>
        <difficult>0</difficult>
        <polygon>
            <x1>2527</x1>
            <y1>834</y1>
            <x2>2751</x2>
            <y2>821</y2>
            <x3>2731</x3>
            <y3>1297</y3>
            <x4>2508</x4>
            <y4>1250</y4>
        </polygon>
        <bndbox>
            <xmin>2508</xmin>
            <ymin>821</ymin>
            <xmax>2751</xmax>
            <ymax>1297</ymax>
        </bndbox>
    </object>
    <object>
        <name>house_number-6546-saint_laurent</name>
        <pose>Unspecified</pose>
        <truncated>0</truncated>
        <occluded>0</occluded>
        <difficult>0</difficult>
        <bndbox>
            <xmin>2586</xmin>
            <ymin>732</ymin>
            <xmax>2691</xmax>
            <ymax>778</ymax>
        </bndbox>
    </object>
    <object>
        <name>house_number-6548-saint_laurent</name>
        <pose>Unspecified</pose>
        <truncated>0</truncated>
        <occluded>0</occluded>
        <difficult>0</difficult>
        <bndbox>
            <xmin>3071</xmin>
            <ymin>460</ymin>
            <xmax>3210</xmax>
            <ymax>541</ymax>
        </bndbox>
    </object>
    <object>
        <name>house_number-6548-saint_laurent</name>
        <pose>Unspecified</pose>
        <truncated>0</truncated>
        <occluded>0</occluded>
        <difficult>0</difficult>
        <bndbox>
            <xmin>3703</xmin>
            <ymin>780</ymin>
            <xmax>3757</xmax>
            <ymax>808</ymax>
        </bndbox>
    </object>
</annotation>