<annotation>
    <folder>panos</folder>
    <filename>pano_003819.png</filename>
    <size>
        <width>3840</width>
        <height>1920</height>
        <depth>3</depth>
    </size>
    <segmented>0</segmented>
    <object>
        <name>street_sign-saint_urbain</name>
        <pose>Unspecified</pose>
        <truncated>0</truncated>
        <occluded>0</occluded>
        <difficult>0</difficult>
        <bndbox>
            <xmin>3406</xmin>
            <ymin>717</ymin>
            <xmax>3491</xmax>
            <ymax>746</ymax>
        </bndbox>
    </object>
</annotation>