<annotation>
    <folder>panos</folder>
    <filename>pano_014543.png</filename>
    <size>
        <width>3840</width>
        <height>1920</height>
        <depth>3</depth>
    </size>
    <segmented>0</segmented>
    <object>
        <name>door-6508-clark</name>
        <pose>Unspecified</pose>
        <truncated>0</truncated>
        <occluded>0</occluded>
        <difficult>0</difficult>
        <polygon>
            <x1>3157</x1>
            <y1>902</y1>
            <x2>3011</x2>
            <y2>883</y2>
            <x3>2991</x3>
            <y3>1261</y3>
            <x4>3129</x4>
            <y4>1250</y4>
        </polygon>
        <bndbox>
            <xmin>2991</xmin>
            <ymin>883</ymin>
            <xmax>3157</xmax>
            <ymax>1261</ymax>
        </bndbox>
    </object>
    <object>
        <name>house_number-6508-clark</name>
        <pose>Unspecified</pose>
        <truncated>0</truncated>
        <occluded>0</occluded>
        <difficult>0</difficult>
        <bndbox>
            <xmin>2925</xmin>
            <ymin>875</ymin>
            <xmax>2978</xmax>
            <ymax>908</ymax>
        </bndbox>
    </object>
</annotation>